fhirtordf/__init__.py
fhirtordf/fhirtordf.py
fhirtordf/fhir/__init__.py
fhirtordf/fhir/fhirmetavoc.py
fhirtordf/fhir/picklejar.py
fhirtordf/fhir/signature.py
fhirtordf/loaders/__init__.py
fhirtordf/loaders/fhircollectionloader.py
fhirtordf/loaders/fhirjsonloader.py
fhirtordf/loaders/fhirresourceloader.md
fhirtordf/loaders/fhirresourceloader.py
fhirtordf/rdfsupport/__init__.py
fhirtordf/rdfsupport/dottednamespace.py
fhirtordf/rdfsupport/fhirgraphutils.py
fhirtordf/rdfsupport/fhirresourcere.py
fhirtordf/rdfsupport/namespaces.py
fhirtordf/rdfsupport/numericnamespace.py
fhirtordf/rdfsupport/prettygraph.py
fhirtordf/rdfsupport/rdfcompare.py
fhirtordf/rdfsupport/rdflibformats.py
fhirtordf/rdfsupport/uriutils.py
fhirtordf-1.3.3.dist-info/AUTHORS
fhirtordf-1.3.3.dist-info/LICENSE
fhirtordf-1.3.3.dist-info/METADATA
fhirtordf-1.3.3.dist-info/WHEEL
fhirtordf-1.3.3.dist-info/entry_points.txt
fhirtordf-1.3.3.dist-info/pbr.json
fhirtordf-1.3.3.dist-info/top_level.txt
fhirtordf-1.3.3.dist-info/RECORD
