Metadata-Version: 2.1
Name: fhirtordf
Version: 1.3.3
Summary: FHIR JSON to RDF Conversion Tool
Home-page: https://github.com/BD2KOnFHIR/fhirtordf
Author: Harold Solbrig
Author-email: solbrig@jhu.edu
License: CC0 1.0 Universal
Keywords: FHIR,rdf
Platform: UNKNOWN
Classifier: Development Status :: 4 - Beta
Classifier: Environment :: Console
Classifier: Intended Audience :: Healthcare Industry
Classifier: Intended Audience :: Science/Research
Classifier: License :: CC0 1.0 Universal (CC0 1.0) Public Domain Dedication
Classifier: Programming Language :: Python :: 3 :: Only
Classifier: Programming Language :: Python :: 3.7
Classifier: Programming Language :: Python :: 3.8
Requires-Dist: dirlistproc (>=1.4.5)
Requires-Dist: isodate
Requires-Dist: jsonasobj (>=1.2.1)
Requires-Dist: python-dateutil
Requires-Dist: rdflib-jsonld
Requires-Dist: rdflib (~=5.0)
